{"data":[{"id":"Eddard_Stark","htmlUrl":"/1/Stark/Eddard_Stark/Eddard_Stark.html","name":"艾德·史塔克","pic":"/1/Stark/Eddard_Stark/Eddard_Stark.png","type":1,"intro":"临冬城公爵、北境守护"},{"id":"Catelyn_Tully","htmlUrl":"/1/Tully/Catelyn_Tully/Catelyn_Tully.html","name":"凯特琳·徒利","pic":"/1/Tully/Catelyn_Tully/Catelyn_Tully.png","type":1,"intro":"临冬城夫人"},{"id":"Robb_Stark","htmlUrl":"/1/Stark/Robb_Stark/Robb_Stark.html","name":"罗伯·史塔克","pic":"/1/Stark/Robb_Stark/Robb_Stark.png","type":1,"intro":"临冬城继承人、“少狼主”"},{"id":"Jon_Snow","htmlUrl":"/1/Stark/Jon_Snow/Jon_Snow.html","name":"琼恩·雪诺","pic":"/1/Stark/Jon_Snow/Jon_Snow.png","type":1,"intro":"“临冬城的私生子“、“囧雪”"},{"id":"Sansa_Stark","htmlUrl":"/1/Stark/Sansa_Stark/Sansa_Stark.html","name":"珊莎·史塔克","pic":"/1/Stark/Sansa_Stark/Sansa_Stark.png","type":1,"intro":"“三傻”"}]}